Metadata-Version: 2.1
Name: argdirective
Version: 0.0.11rc1
Summary: Argdirective is a python module to detect the first command line argument as subcommand.
Home-page: https://gitlab.com/domsonAut/argdirective
Author: Dominik Kummer
Author-email: admin@arkades.org
License: UNKNOWN
Project-URL: Bug Reports, https://gitlab.com/domsonAut/argdirective/issues
Project-URL: Source, https://gitlab.com/domsonAut/argdirective/
Keywords: shell argument directive
Platform: UNKNOWN
Classifier: Development Status :: 3 - Alpha
Classifier: Intended Audience :: Developers
Classifier: Topic :: Software Development :: User Interfaces
Classifier: License :: OSI Approved :: GNU General Public License v3 (GPLv3)
Classifier: Programming Language :: Python :: 3.7
Requires-Python: >=3
